{
  "expertise": "BEGINNER",
  "version": 1,
  "source": "github",
  "authorIds": [
    "kaushalvasava"
  ],
  "owner": "KaushalVasava",
  "repo": "Instagram",
  "name": "Instagram Clone using Jetpack Compose",
  "shortDescription": "It is an Instagram clone using Jetpack compose. I used dependency Injection, Retrofit2, Viewpager, Coil, Tab-layout, MVVM architecture, Flow, bottom-navigation, navigation graph, and animations.",
  "longDescription": "It is an Instagram clone using Jetpack compose. I used dependency Injection, Retrofit2, Viewpager, Coil, Tab-layout, MVVM architecture, Flow, bottom-navigation, navigation graph, and animations.",
  "content": "README.md",
  "pages": [],
  "tags": [
    "compose",
    "modern-android-development",
    "kotlin"
  ]
}
