{
  "expertise": "INTERMEDIATE",
  "version": 1,
  "source": "github",
  "authorIds": [
    "vthinkxie"
  ],
  "owner": "NG-ZORRO",
  "repo": "ng-zorro-antd",
  "name": "ng-zorro-antd",
  "shortDescription": "An enterprise-class Angular UI component library based on Ant Design, all components are open source and free to use under MIT license.",
  "longDescription": "An enterprise-class Angular UI component library based on Ant Design, all components are open source and free to use under MIT license.",
  "content": "README.md",
  "pages": [],
  "tags": [
    "components",
    "frameworks"
  ]
}
