{
  "expertise": "BEGINNER",
  "version": 1,
  "source": "other",
  "authorIds": [
    "subhadiptech"
  ],
  "author": "Subhadip Das",
  "title": "Why sealed class exists in Koltin",
  "link": "https://learndroid.hashnode.dev/why-kotlin-sealed-class-exists",
  "tags": [
    "kotlin",
    "modern-android-development"
  ],
  "description": "Kotlin, being an emerging open-source programming language provides lesser boilerplate and also some additional features which help manage the code flow better. Let's check out sealed classes and its features here."
}
