{
  "expertise": "BEGINNER",
  "version": 1,
  "source": "github",
  "authorIds": [
    "xavidop"
  ],
  "owner": "xavidop",
  "repo": "dialogflow-cx-messenger-ts",
  "name": "Typescript Types for Dialogflow CX Messenger Integ",
  "shortDescription": "Typescript classes and types to use Dialogflow Messenger Integration in Typescript.",
  "longDescription": "Typescript classes and types to use Dialogflow Messenger Integration in Typescript.",
  "content": "README.md",
  "pages": [],
  "tags": [
    "other-google-ml-products"
  ]
}
